wtee/__init__.py
wtee/__main__.py
wtee/main.py
wtee/server.py
wtee/utils.py
wtee/assets/cog.svg
wtee/assets/favicon.ico
wtee/assets/gen/.keep
wtee/assets/gen/3rdparty.css
wtee/assets/gen/3rdparty.js
wtee/assets/gen/Main.js
wtee/assets/gen/Main.js.map
wtee/assets/gen/Main.min.js
wtee/assets/gen/main.css
wtee/templates/base.html
wtee/templates/wtee.html
wtee-1.2.0.dist-info/METADATA
wtee-1.2.0.dist-info/RECORD
wtee-1.2.0.dist-info/WHEEL
wtee-1.2.0.dist-info/entry_points.txt
wtee-1.2.0.dist-info/top_level.txt
wtee-1.2.0.dist-info/zip-safe
