Metadata-Version: 2.1
Name: wtee
Version: 1.2.0
Summary: read from stdin, write to stdout and serve on a webpage
Home-page: https://github.com/gvalkov/wtee
Author: Georgi Valkov
Author-email: georgi.t.valkov@gmail.com
License: Revised BSD License
Keywords: log tee tail
Platform: UNKNOWN
Classifier: Development Status :: 5 - Production/Stable
Classifier: Programming Language :: Python :: 2.7
Classifier: Programming Language :: Python :: 3
Classifier: License :: OSI Approved :: BSD License
Classifier: Intended Audience :: Developers
Requires-Dist: tornado (<5.0.0,>=4.0.0)
Requires-Dist: sockjs-tornado (>=1.0.0)
